spherenet/__init__.py
spherenet/layers.py
spherenet/primitives.py
spherenet/test_layers.py
spherenet/test_primitives.py
spherenet-0.0.3.dist-info/DESCRIPTION.rst
spherenet-0.0.3.dist-info/METADATA
spherenet-0.0.3.dist-info/RECORD
spherenet-0.0.3.dist-info/WHEEL
spherenet-0.0.3.dist-info/metadata.json
spherenet-0.0.3.dist-info/top_level.txt
